inflate/__init__.py
inflate/__main__.py
inflate/cli.py
inflate/inflate.py
inflate/main.py
inflate/data/uk_inflation.json
inflate/data/us_inflation.json
inflate-0.1rc3.dist-info/LICENSE
inflate-0.1rc3.dist-info/METADATA
inflate-0.1rc3.dist-info/WHEEL
inflate-0.1rc3.dist-info/entry_points.txt
inflate-0.1rc3.dist-info/top_level.txt
inflate-0.1rc3.dist-info/RECORD
