Metadata-Version: 2.1
Name: inflate
Version: 0.1rc3
Summary: inflate lets you compute how much money is worth in different years
Home-page: https://github.com/mzjp2/inflate
Author: Zain Patel
Author-email: zain.patel06@gmail.com
License: UNKNOWN
Keywords: money command line interface inflation cli
Platform: UNKNOWN
Classifier: Programming Language :: Python :: 3
Classifier: License :: OSI Approved :: MIT License
Classifier: Operating System :: OS Independent
Requires-Python: >=3.5
Requires-Dist: click
Requires-Dist: colorama
